robloxpyc/__init__.py
robloxpyc/basecompilers.py
robloxpyc/bindings.py
robloxpyc/binopdesc.py
robloxpyc/boolopdesc.py
robloxpyc/climaker.py
robloxpyc/cmpopdesc.py
robloxpyc/cnodevisitor.py
robloxpyc/colortext.py
robloxpyc/config.py
robloxpyc/configmanager.py
robloxpyc/context.py
robloxpyc/cpAST.py
robloxpyc/ctranslator.py
robloxpyc/errormanager.py
robloxpyc/header.py
robloxpyc/installationmanager.py
robloxpyc/loader.py
robloxpyc/loopcounter.py
robloxpyc/luainit.py
robloxpyc/luainitlua.lua
robloxpyc/model.py
robloxpyc/nameconstdesc.py
robloxpyc/nodevisitor.py
robloxpyc/parser.py
robloxpyc/plugin.py
robloxpyc/pytranslator.py
robloxpyc/reporter.py
robloxpyc/robloxpy.py
robloxpyc/symbolsstack.py
robloxpyc/textcompiler.py
robloxpyc/tokenendmode.py
robloxpyc/unaryopdesc.py
robloxpyc/util.py
robloxpyc/wally.py
robloxpyc/writer.py
robloxpyc/LuauAST/bundle.ts
robloxpyc/LuauAST/index.ts
robloxpyc/LuauAST/impl/List.ts
robloxpyc/LuauAST/impl/create.ts
robloxpyc/LuauAST/impl/enums.ts
robloxpyc/LuauAST/impl/globals.ts
robloxpyc/LuauAST/impl/strings.ts
robloxpyc/LuauAST/impl/typeGuards.ts
robloxpyc/LuauAST/types/mapping.ts
robloxpyc/LuauAST/types/nodes.ts
robloxpyc/LuauAST/types/operators.ts
robloxpyc/LuauAST/util/assert.ts
robloxpyc/LuauAST/util/getKindName.ts
robloxpyc/LuauAST/util/isMetamethod.ts
robloxpyc/LuauAST/util/isReservedClassField.ts
robloxpyc/LuauAST/util/isReservedIdentifier.ts
robloxpyc/LuauAST/util/isValidIdentifier.ts
robloxpyc/LuauAST/util/isValidNumberLiteral.ts
robloxpyc/LuauRenderer/RenderState.ts
robloxpyc/LuauRenderer/index.ts
robloxpyc/LuauRenderer/render.ts
robloxpyc/LuauRenderer/solveTempIds.ts
robloxpyc/LuauRenderer/nodes/expressions/renderArray.ts
robloxpyc/LuauRenderer/nodes/expressions/renderBinaryExpression.ts
robloxpyc/LuauRenderer/nodes/expressions/renderFunctionExpression.ts
robloxpyc/LuauRenderer/nodes/expressions/renderIfExpression.ts
robloxpyc/LuauRenderer/nodes/expressions/renderMap.ts
roblox_pyc-2.26.113.dist-info/LICENSE
roblox_pyc-2.26.113.dist-info/METADATA
roblox_pyc-2.26.113.dist-info/WHEEL
roblox_pyc-2.26.113.dist-info/entry_points.txt
roblox_pyc-2.26.113.dist-info/top_level.txt
roblox_pyc-2.26.113.dist-info/RECORD
