Metadata-Version: 2.1
Name: roblox-pyc
Version: 2.26.113
Summary: The Python, Lunar, C, C++ to Roblox Lua compiler
Home-page: https://github.com/AsynchronousAI/roblox.pyc
Author: roblox-pyc team
Author-email: roblox.pyc@gmail.com
License: GNU AFFERO GENERAL PUBLIC LICENSE
License-File: LICENSE
Requires-Dist: clang
Requires-Dist: libclang
Requires-Dist: typer
Requires-Dist: flask
Requires-Dist: pyflakes
Requires-Dist: pyyaml
Requires-Dist: tqdm
Requires-Dist: requests
Requires-Dist: packaging
